sqlite_storage/__init__.py
sqlite_storage/sqlite_storage.py
sqlite_storage-1.0.3.dist-info/METADATA
sqlite_storage-1.0.3.dist-info/WHEEL
sqlite_storage-1.0.3.dist-info/top_level.txt
sqlite_storage-1.0.3.dist-info/RECORD
