Metadata-Version: 2.1
Name: sqlite_storage
Version: 1.0.3
Summary: SQLite storage for aiogram bots.
Author-email: osf4 <12y98431c29y4@mail.ru>
Project-URL: Homepage, https://github.com/osf4/sqlite_storage
Project-URL: Issues, https://github.com/osf4/sqlite_storage/issues
Classifier: Programming Language :: Python :: 3
Classifier: Operating System :: OS Independent
Requires-Python: >=3.8
